SabertoothPacketSerial/SabertoothPacketSerial.py
SabertoothPacketSerial/__init__.py
SabertoothPacketSerial/version.py
SabertoothPacketSerial-0.2.2.dist-info/LICENSE
SabertoothPacketSerial-0.2.2.dist-info/METADATA
SabertoothPacketSerial-0.2.2.dist-info/WHEEL
SabertoothPacketSerial-0.2.2.dist-info/top_level.txt
SabertoothPacketSerial-0.2.2.dist-info/RECORD
