Metadata-Version: 2.1
Name: SabertoothPacketSerial
Version: 0.2.2
Summary: Library for Dimenson Engineering Sabertooth speed controller
Home-page: https://github.com/dpoulson/SabertoothPacketSerial
Author: Darren Poulson
Author-email: darren.poulson@gmail.com
License: GPL
Platform: UNKNOWN
